bree
