Metadata-Version: 1.1
Name: bree
Version: 0.1.2
Summary: a micro library for happy coding tornado.
Home-page: UNKNOWN
Author: WANG WENPEI
Author-email: wangwenpei@nextoa.com
License: http://opensource.org/licenses/MIT
Download-URL: https://github.com/nextoa/bree/archive/master.zip
Keywords: tornado
Platform: UNKNOWN
